quixote/__init__.py
quixote/build/__init__.py
quixote/build/apt.py
quixote/build/debconf.py
quixote/build/installs.py
quixote/build/output.py
quixote/build/pip.py
quixote/build/shell.py
quixote/build/utils.py
quixote/fetch/__init__.py
quixote/fetch/copy.py
quixote/fetch/git.py
quixote/fetch/gitlab.py
quixote/inspection/__init__.py
quixote/inspection/_errors.py
quixote/inspection/_inspection_result.py
quixote/inspection/_message.py
quixote/inspection/build.py
quixote/inspection/check.py
quixote/inspection/diff.py
quixote/inspection/exec.py
quixote/inspection/pushd.py
etna_quixote-2.4.1.dist-info/WHEEL
etna_quixote-2.4.1.dist-info/METADATA
etna_quixote-2.4.1.dist-info/RECORD
