Metadata-Version: 2.1
Name: etna-quixote
Version: 2.4.1
Summary: Front-end to write automated tests for Etna projects
License: MIT
Author: Clément "Doom" Doumergue
Author-email: clement.doumergue@etna.io
Requires-Python: >=3.8,<4.0
Classifier: License :: OSI Approved :: MIT License
Classifier: Programming Language :: Python :: 3
Classifier: Programming Language :: Python :: 3.10
Classifier: Programming Language :: Python :: 3.8
Classifier: Programming Language :: Python :: 3.9
Requires-Dist: GitPython (>=3.1.29,<4.0.0)
Requires-Dist: etna-api (>=3.0.0,<4.0.0)
Requires-Dist: requests (>=2.28.0,<3.0.0)
